setup.cfg
setup.py
aws_monocyte.egg-info/PKG-INFO
aws_monocyte.egg-info/SOURCES.txt
aws_monocyte.egg-info/dependency_links.txt
aws_monocyte.egg-info/requires.txt
aws_monocyte.egg-info/top_level.txt
aws_monocyte.egg-info/zip-safe
monocyte/__init__.py
monocyte/cli.py
monocyte/handler/__init__.py
monocyte/handler/acm.py
monocyte/handler/cloudformation.py
monocyte/handler/dynamodb.py
monocyte/handler/ec2.py
monocyte/handler/iam.py
monocyte/handler/rds2.py
monocyte/handler/s3.py
monocyte/plugins/__init__.py
monocyte/plugins/ses_plugin.py
monocyte/plugins/sqs_plugin.py
monocyte/plugins/status_mail_plugin.py
scripts/monocyte