Metadata-Version: 1.1
Name: aws-monocyte
Version: 0.3.509.post312
Summary: Monocyte - Search and Destroy unwanted AWS Resources relentlessly.
Home-page: https://github.com/ImmobilienScout24/aws-monocyte
Author: Jan Brennenstuhl, Arne Hilmann
Author-email: jan@brennenstuhl.me, arne.hilmann@gmail.com
License: Apache License 2.0
Platform: UNKNOWN
Classifier: Development Status :: 4 - Beta
Classifier: Environment :: Console
Classifier: Intended Audience :: Developers
Classifier: Intended Audience :: System Administrators
Classifier: Programming Language :: Python
Classifier: Topic :: System :: Networking
Classifier: Topic :: System :: Software Distribution
Classifier: Topic :: System :: Systems Administration
